<annotation>
	<folder>images</folder>
	<filename>20190103_220905.jpg</filename>
	<path>/home/aaron/Documents/workspace/my_github/mtg_card_master/data/bounding_box/images/20190103_220905.jpg</path>
	<source>
		<database>Unknown</database>
	</source>
	<size>
		<width>4032</width>
		<height>2268</height>
		<depth>3</depth>
	</size>
	<segmented>0</segmented>
	<object>
		<name>Card</name>
		<pose>Unspecified</pose>
		<truncated>0</truncated>
		<difficult>0</difficult>
		<bndbox>
			<xmin>974</xmin>
			<ymin>86</ymin>
			<xmax>2196</xmax>
			<ymax>1121</ymax>
		</bndbox>
	</object>
	<object>
		<name>Card</name>
		<pose>Unspecified</pose>
		<truncated>0</truncated>
		<difficult>0</difficult>
		<bndbox>
			<xmin>2118</xmin>
			<ymin>347</ymin>
			<xmax>3405</xmax>
			<ymax>1390</ymax>
		</bndbox>
	</object>
	<object>
		<name>Card</name>
		<pose>Unspecified</pose>
		<truncated>0</truncated>
		<difficult>0</difficult>
		<bndbox>
			<xmin>1935</xmin>
			<ymin>1216</ymin>
			<xmax>3179</xmax>
			<ymax>2238</ymax>
		</bndbox>
	</object>
	<object>
		<name>Card</name>
		<pose>Unspecified</pose>
		<truncated>0</truncated>
		<difficult>0</difficult>
		<bndbox>
			<xmin>818</xmin>
			<ymin>929</ymin>
			<xmax>2000</xmax>
			<ymax>1942</ymax>
		</bndbox>
	</object>
</annotation>
